MANIFEST.in
setup.cfg
setup.py
isso/__init__.py
isso/compat.py
isso/config.py
isso/core.py
isso/defaults.ini
isso/dispatch.py
isso/migrate.py
isso/run.py
isso/wsgi.py
isso/db/__init__.py
isso/db/comments.py
isso/db/openid.py
isso/db/preferences.py
isso/db/spam.py
isso/db/threads.py
isso/ext/__init__.py
isso/ext/notifications.py
isso/ext/openid.py
isso/images/facebook-color.png
isso/images/googleplus-color.png
isso/images/openid-icon-32x32.png
isso/js/count.dev.js
isso/js/count.min.js
isso/js/embed.dev.js
isso/js/embed.min.js
isso/utils/__init__.py
isso/utils/hash.py
isso/utils/html.py
isso/utils/http.py
isso/utils/parse.py
isso/views/__init__.py
isso/views/comments.py
isso_social.egg-info/PKG-INFO
isso_social.egg-info/SOURCES.txt
isso_social.egg-info/dependency_links.txt
isso_social.egg-info/entry_points.txt
isso_social.egg-info/not-zip-safe
isso_social.egg-info/requires.txt
isso_social.egg-info/top_level.txt
man/man1/isso.1
man/man5/isso.conf.5
share/isso.conf