Metadata-Version: 1.1
Name: isso-social
Version: 0.10.7.5
Summary: lightweight Disqus alternative
Home-page: https://github.com/pellenilsson/isso
Author: Pelle Nilsson
Author-email: pellenilsson@fastmail.fm
License: MIT
Platform: UNKNOWN
Classifier: Development Status :: 4 - Beta
Classifier: Topic :: Internet
Classifier: Topic :: Internet :: WWW/HTTP :: HTTP Servers
Classifier: Topic :: Internet :: WWW/HTTP :: WSGI :: Application
Classifier: License :: OSI Approved :: MIT License
Classifier: Programming Language :: Python :: 2.6
Classifier: Programming Language :: Python :: 2.7
Classifier: Programming Language :: Python :: 3.3
Classifier: Programming Language :: Python :: 3.4
